bob/__init__.py
bob/bio/__init__.py
bob/bio/base/__init__.py
bob/bio/base/wrappers.py
bob/bio/base/algorithm/__init__.py
bob/bio/base/algorithm/distance.py
bob/bio/base/algorithm/gmm.py
bob/bio/base/algorithm/isv.py
bob/bio/base/algorithm/jfa.py
bob/bio/base/annotator/Annotator.py
bob/bio/base/annotator/Callable.py
bob/bio/base/annotator/FailSafe.py
bob/bio/base/annotator/__init__.py
bob/bio/base/config/__init__.py
bob/bio/base/config/database/__init__.py
bob/bio/base/config/database/atnt.py
bob/bio/base/config/dummy/__init__.py
bob/bio/base/config/dummy/annotator.py
bob/bio/base/config/dummy/config.py
bob/bio/base/config/dummy/config2.py
bob/bio/base/config/dummy/database.py
bob/bio/base/config/dummy/extractor.py
bob/bio/base/config/dummy/pipeline.py
bob/bio/base/config/dummy/preprocessor.py
bob/bio/base/config/dummy/samples_list.py
bob/bio/base/database/__init__.py
bob/bio/base/database/atnt.py
bob/bio/base/database/csv_database.py
bob/bio/base/database/database.py
bob/bio/base/database/file.py
bob/bio/base/database/legacy.py
bob/bio/base/database/utils.py
bob/bio/base/database/filelist/__init__.py
bob/bio/base/database/filelist/models.py
bob/bio/base/database/filelist/query.py
bob/bio/base/extractor/Extractor.py
bob/bio/base/extractor/__init__.py
bob/bio/base/pipelines/__init__.py
bob/bio/base/pipelines/abstract_classes.py
bob/bio/base/pipelines/entry_points.py
bob/bio/base/pipelines/pipelines.py
bob/bio/base/pipelines/score_post_processor.py
bob/bio/base/pipelines/score_writers.py
bob/bio/base/pipelines/wrappers.py
bob/bio/base/preprocessor/Preprocessor.py
bob/bio/base/preprocessor/__init__.py
bob/bio/base/score/__init__.py
bob/bio/base/score/load.py
bob/bio/base/script/__init__.py
bob/bio/base/script/annotate.py
bob/bio/base/script/bio.py
bob/bio/base/script/commands.py
bob/bio/base/script/compare_samples.py
bob/bio/base/script/error_utils.py
bob/bio/base/script/figure.py
bob/bio/base/script/gen.py
bob/bio/base/script/pipeline.py
bob.bio.base-8.1.1.dist-info/LICENSE
bob.bio.base-8.1.1.dist-info/METADATA
bob.bio.base-8.1.1.dist-info/WHEEL
bob.bio.base-8.1.1.dist-info/entry_points.txt
bob.bio.base-8.1.1.dist-info/top_level.txt
bob.bio.base-8.1.1.dist-info/RECORD
