Metadata-Version: 2.1
Name: bob.bio.base
Version: 8.1.1
Summary: Tools for running biometric recognition experiments
Author-email: Manuel Gunther <siebenkopf@googlemail.com>
License: BSD 3-Clause License
Project-URL: documentation, https://www.idiap.ch/software/bob/docs/bob/bob.bio.base/v8.1.1/sphinx/
Project-URL: homepage, https://pypi.org/project/bob.bio.base/
Project-URL: repository, https://gitlab.idiap.ch/bob/bob.bio.base
Project-URL: changelog, https://gitlab.idiap.ch/bob/bob.bio.base/-/releases
Keywords: bob,biometric recognition,evaluation
Classifier: Framework :: Bob
Classifier: Development Status :: 3 - Alpha
Classifier: Intended Audience :: Developers
Classifier: License :: OSI Approved :: BSD License
Classifier: Natural Language :: English
Classifier: Programming Language :: Python
Classifier: Topic :: Scientific/Engineering :: Artificial Intelligence
Requires-Python: >=3.9
License-File: LICENSE
Requires-Dist: bob ==12.1.1
Requires-Dist: bob.io.base ==5.1.1
Requires-Dist: bob.learn.em ==3.3.1
Requires-Dist: bob.measure ==6.1.1
Requires-Dist: bob.pipelines ==4.0.1
Requires-Dist: clapper ~=1.0
Requires-Dist: click ~=8.1
Requires-Dist: click-plugins ~=1.1
Requires-Dist: dask ==2024.5.2
Requires-Dist: numpy ~=1.26
Requires-Dist: pandas ~=2.2
Requires-Dist: scipy ~=1.10
Requires-Dist: tabulate ~=0.9
Provides-Extra: doc
Requires-Dist: sphinx ; extra == 'doc'
Requires-Dist: sphinx-rtd-theme ; extra == 'doc'
Requires-Dist: sphinx-autodoc-typehints ; extra == 'doc'
Requires-Dist: auto-intersphinx ; extra == 'doc'
Requires-Dist: sphinxcontrib-programoutput ; extra == 'doc'
Requires-Dist: matplotlib ; extra == 'doc'
Requires-Dist: dask-ml ; extra == 'doc'
Provides-Extra: qa
Requires-Dist: pre-commit ; extra == 'qa'
Provides-Extra: test
Requires-Dist: pytest ; extra == 'test'
Requires-Dist: pytest-cov ; extra == 'test'
Requires-Dist: coverage ; extra == 'test'
Requires-Dist: dask-ml ; extra == 'test'
Requires-Dist: matplotlib ; extra == 'test'
